MANIFEST.in
README.md
setup.cfg
setup.py
PoE.py.egg-info/PKG-INFO
PoE.py.egg-info/SOURCES.txt
PoE.py.egg-info/dependency_links.txt
PoE.py.egg-info/top_level.txt
poe/__init__.py
poe/client.py
poe/clientbase.py
poe/constants.py
poe/exceptions.py
poe/models.py
poe/utils.py
poe/data/Fontin-SmallCaps.ttf
poe/data/Fontin-SmallCapsItalic.ttf
poe/data/ascendancy.json
poe/data/ascendancy_frame.png
poe/data/div_frame.png
poe/data/elder_badge.png
poe/data/elder_bg_1x1.png
poe/data/elder_bg_1x3.png
poe/data/elder_bg_1x4.png
poe/data/elder_bg_2x1.png
poe/data/elder_bg_2x2.png
poe/data/elder_bg_2x3.png
poe/data/elder_bg_2x4.png
poe/data/gem_namebar_left.png
poe/data/gem_namebar_right.png
poe/data/gem_namebar_trans.png
poe/data/gem_separator.png
poe/data/keystone_frame.png
poe/data/keystones.json
poe/data/magic_namebar_left.png
poe/data/magic_namebar_right.png
poe/data/magic_namebar_trans.png
poe/data/magic_separator.png
poe/data/normal_namebar_left.png
poe/data/normal_namebar_right.png
poe/data/normal_namebar_trans.png
poe/data/normal_separator.png
poe/data/notable_frame.png
poe/data/passive_frame.png
poe/data/prophecy_namebar_left.png
poe/data/prophecy_namebar_right.png
poe/data/prophecy_namebar_trans.png
poe/data/prophecy_separator.png
poe/data/rare_namebar_left.png
poe/data/rare_namebar_right.png
poe/data/rare_namebar_trans.png
poe/data/rare_separator.png
poe/data/relic_namebar_left.png
poe/data/relic_namebar_right.png
poe/data/relic_namebar_trans.png
poe/data/relic_separator.png
poe/data/shaper_badge.png
poe/data/shaper_bg_1x1.png
poe/data/shaper_bg_1x2.png
poe/data/shaper_bg_1x3.png
poe/data/shaper_bg_1x4.png
poe/data/shaper_bg_2x1.png
poe/data/shaper_bg_2x2.png
poe/data/shaper_bg_2x3.png
poe/data/shaper_bg_2x4.png
poe/data/silver_coin.png
poe/data/unique_namebar_left.png
poe/data/unique_namebar_right.png
poe/data/unique_namebar_trans.png
poe/data/unique_separator.png
poe/data/valid_filters.json