Metadata-Version: 2.1
Name: PoE.py
Version: 2.0.3a0
Summary: A Path of Exile wrapper/lib that supports multitudes of filters to list and render items as PNGs and retreive useful character data.
Home-page: https://github.com/xKynn/PoE.py
Author: xKynn
Author-email: xkynn@github.com
License: UNKNOWN
Platform: UNKNOWN
Classifier: License :: OSI Approved :: MIT License
Classifier: Operating System :: OS Independent
